jvnpack/hello.py
jvnpack/harmonic_mean.pyx
jvnpack/__init__.py
jvnpack/harmony.py
jvnpack/data.json
jvnpack/harmonic_mean.c
jvnpack/harmonic_mean.pypy38-pp73-darwin.so
pubpypack_harmony_jan_vium-0.0.4.dist-info/RECORD
pubpypack_harmony_jan_vium-0.0.4.dist-info/LICENSE
pubpypack_harmony_jan_vium-0.0.4.dist-info/WHEEL
pubpypack_harmony_jan_vium-0.0.4.dist-info/entry_points.txt
pubpypack_harmony_jan_vium-0.0.4.dist-info/top_level.txt
pubpypack_harmony_jan_vium-0.0.4.dist-info/METADATA
