Metadata-Version: 2.1
Name: pubpypack-harmony-jan-vium
Version: 0.0.4
Summary: This is an initial package.
Home-page: http://localhost
Author: Jan Vium Enghoff
Author-email: "Example" <test@example.com>
License: MIT
Classifier: License :: OSI Approved :: MIT License
Requires-Python: >=3.8
License-File: LICENSE
Requires-Dist: termcolor (<2,>=1.1.0)
